{
  "tracks": {
    "genres": {
      "pop": [
        {
          "title": "Dance Away",
          "author": "Samantha Smith",
          "price": 0.99,
          "url": "https://example.com/dance_away",
          "imageUrl": "https://encrypted-tbn0.gstatic.com/images?q=tbn:ANd9GcSw94caeZ4CJUJh6ooi_oS-s1lpomXXvxarDg&usqp=CAU",
          "length": "3:45",
          "rating": 4.5,
          "genre": "pop",
          "tags": ["upbeat", "summer", "party"]
        },
        {
          "title": "Starlight",
          "author": "Maxwell Parker",
          "price": 1.29,
          "url": "https://example.com/dance_away",
          "imageUrl": "https://encrypted-tbn0.gstatic.com/images?q=tbn:ANd9GcSw94caeZ4CJUJh6ooi_oS-s1lpomXXvxarDg&usqp=CAU",
          "length": "4:10",
          "rating": 4.2,
          "tags": ["love", "romance", "melodic"]
        },
        {
          "title": "Funky Groove",
          "author": "Sophie Funk",
          "price": 1.19,
          "url": "https://example.com/dance_away",
          "imageUrl": "https://encrypted-tbn0.gstatic.com/images?q=tbn:ANd9GcSw94caeZ4CJUJh6ooi_oS-s1lpomXXvxarDg&usqp=CAU",
          "length": "3:30",
          "rating": 4.1,
          "tags": ["funky", "dance", "groove"]
        },
        {
          "title": "Sunshine Beat",
          "author": "Jimmy Summer",
          "price": 0.89,
          "url": "https://example.com/dance_away",
          "imageUrl": "https://encrypted-tbn0.gstatic.com/images?q=tbn:ANd9GcSw94caeZ4CJUJh6ooi_oS-s1lpomXXvxarDg&usqp=CAU",
          "length": "4:05",
          "rating": 4.4,
          "tags": ["uplifting", "feel-good", "joyful"]
        },
        {
          "title": "Party Anthem",
          "author": "DJ Max",
          "price": 1.49,
          "url": "https://example.com/dance_away",
          "imageUrl": "https://encrypted-tbn0.gstatic.com/images?q=tbn:ANd9GcSw94caeZ4CJUJh6ooi_oS-s1lpomXXvxarDg&usqp=CAU",
          "length": "3:55",
          "rating": 4.7,
          "tags": ["energetic", "celebration", "dancefloor"]
        }
      ],
      "rock": [
        {
          "title": "Revolution",
          "author": "The Rebels",
          "price": 1.49,
          "url": "https://example.com/dance_away",
          "imageUrl": "https://encrypted-tbn0.gstatic.com/images?q=tbn:ANd9GcSw94caeZ4CJUJh6ooi_oS-s1lpomXXvxarDg&usqp=CAU",
          "length": "5:20",
          "rating": 4.7,
          "tags": ["energetic", "protest", "anthem"]
        },
        {
          "title": "Wildfire",
          "author": "Phoenix Rising",
          "price": 0.89,
          "url": "https://example.com/dance_away",
          "imageUrl": "https://encrypted-tbn0.gstatic.com/images?q=tbn:ANd9GcSw94caeZ4CJUJh6ooi_oS-s1lpomXXvxarDg&usqp=CAU",
          "length": "3:30",
          "rating": 4.3,
          "tags": ["powerful", "driving", "intense"]
        },
        {
          "title": "Thunderstruck",
          "author": "Storm Riders",
          "price": 1.99,
          "url": "https://example.com/dance_away",
          "imageUrl": "https://encrypted-tbn0.gstatic.com/images?q=tbn:ANd9GcSw94caeZ4CJUJh6ooi_oS-s1lpomXXvxarDg&usqp=CAU",
          "length": "4:45",
          "rating": 4.8,
          "tags": ["electric", "thunderous", "loud"]
        },
        {
          "title": "Rebel's Call",
          "author": "Johnny Blaze",
          "price": 1.29,
          "url": "https://example.com/dance_away",
          "imageUrl": "https://encrypted-tbn0.gstatic.com/images?q=tbn:ANd9GcSw94caeZ4CJUJh6ooi_oS-s1lpomXXvxarDg&usqp=CAU",
          "length": "4:10",
          "rating": 4.6,
          "tags": ["rebellion", "roar", "freedom"]
        },
        {
          "title": "Savage Heart",
          "author": "Raging Lions",
          "price": 1.39,
          "url": "https://example.com/dance_away",
          "imageUrl": "https://encrypted-tbn0.gstatic.com/images?q=tbn:ANd9GcSw94caeZ4CJUJh6ooi_oS-s1lpomXXvxarDg&usqp=CAU",
          "length": "3:55",
          "rating": 4.4,
          "tags": ["wild", "untamed", "passionate"]
        }
      ],
      "electronic": [
        {
          "title": "Digital Dreams",
          "author": "Neon Soundwave",
          "price": 1.99,
          "url": "https://example.com/dance_away",
          "imageUrl": "https://encrypted-tbn0.gstatic.com/images?q=tbn:ANd9GcSw94caeZ4CJUJh6ooi_oS-s1lpomXXvxarDg&usqp=CAU",
          "length": "6:15",
          "rating": 4.6,
          "tags": ["futuristic", "synth", "edm"]
        },
        {
          "title": "Neon Nights",
          "author": "Cyber Funk",
          "price": 1.39,
          "url": "https://example.com/dance_away",
          "imageUrl": "https://encrypted-tbn0.gstatic.com/images?q=tbn:ANd9GcSw94caeZ4CJUJh6ooi_oS-s1lpomXXvxarDg&usqp=CAU",
          "length": "4:45",
          "rating": 4.4,
          "tags": ["groovy", "techno", "club"]
        },
        {
          "title": "Electric City",
          "author": "Voltage",
          "price": 1.69,
          "url": "https://example.com/dance_away",
          "imageUrl": "https://encrypted-tbn0.gstatic.com/images?q=tbn:ANd9GcSw94caeZ4CJUJh6ooi_oS-s1lpomXXvxarDg&usqp=CAU",
          "length": "5:30",
          "rating": 4.5,
          "tags": ["electro", "urban", "energetic"]
        },
        {
          "title": "Synth Symphony",
          "author": "Digital Harmony",
          "price": 1.79,
          "url": "https://example.com/dance_away",
          "imageUrl": "https://encrypted-tbn0.gstatic.com/images?q=tbn:ANd9GcSw94caeZ4CJUJh6ooi_oS-s1lpomXXvxarDg&usqp=CAU",
          "length": "6:00",
          "rating": 4.7,
          "tags": ["synthwave", "retro", "nostalgic"]
        },
        {
          "title": "Club Beats",
          "author": "DJ Spin",
          "price": 1.19,
          "url": "https://example.com/dance_away",
          "imageUrl": "https://encrypted-tbn0.gstatic.com/images?q=tbn:ANd9GcSw94caeZ4CJUJh6ooi_oS-s1lpomXXvxarDg&usqp=CAU",
          "length": "4:20",
          "rating": 4.3,
          "tags": ["club", "dance", "vibes"]
        }
      ]
    },
    "trending": [
      {
        "title": "Sunset Vibes",
        "author": "Chill Lounge",
        "price": 0.79,
        "url": "https://example.com/dance_away",
        "imageUrl": "https://encrypted-tbn0.gstatic.com/images?q=tbn:ANd9GcSw94caeZ4CJUJh6ooi_oS-s1lpomXXvxarDg&usqp=CAU",
        "length": "3:00",
        "rating": 4.8,
        "genre": "chill",
        "tags": ["relaxing", "ambient", "chillout"]
      },
      {
        "title": "Midnight Drive",
        "author": "Night Cruisers",
        "price": 1.59,
        "url": "https://example.com/dance_away",
        "imageUrl": "https://encrypted-tbn0.gstatic.com/images?q=tbn:ANd9GcSw94caeZ4CJUJh6ooi_oS-s1lpomXXvxarDg&usqp=CAU",
        "length": "5:45",
        "rating": 4.9,
        "genre": "synthwave",
        "tags": ["retro", "nostalgic", "80s"]
      },
      {
        "title": "Midnight Drive",
        "author": "Night Cruisers",
        "price": 1.59,
        "url": "https://example.com/dance_away",
        "imageUrl": "https://encrypted-tbn0.gstatic.com/images?q=tbn:ANd9GcSw94caeZ4CJUJh6ooi_oS-s1lpomXXvxarDg&usqp=CAU",
        "length": "5:45",
        "rating": 4.9,
        "genre": "synthwave",
        "tags": ["retro", "nostalgic", "80s"]
      }
    ]
  }
}
